LICENSE
MANIFEST.in
README.md
requirements.txt
setup.cfg
setup.py
versioneer.py
src/clusterpolate/__init__.py
src/clusterpolate.egg-info/PKG-INFO
src/clusterpolate.egg-info/SOURCES.txt
src/clusterpolate.egg-info/dependency_links.txt
src/clusterpolate.egg-info/requires.txt
src/clusterpolate.egg-info/top_level.txt