Metadata-Version: 1.1
Name: clusterpolate
Version: 0.2.0
Summary: Clusterpolate: Inter- and extrapolation for clustered data.
Home-page: https://github.com/torfsen/clusterpolate
Author: Florian Brucker
Author-email: mail@florianbrucker.de
License: MIT
Keywords: interpolation,extrapolation,data,cluster,scattered,heatmap,scatterplot
Platform: UNKNOWN
Classifier: Development Status :: 4 - Beta
Classifier: Intended Audience :: Developers
Classifier: Intended Audience :: Science/Research
Classifier: License :: OSI Approved :: MIT License
Classifier: Operating System :: POSIX
Classifier: Programming Language :: Python :: 2
Classifier: Programming Language :: Python :: 2.7
Classifier: Programming Language :: Python :: 3
Classifier: Programming Language :: Python :: 3.4
Classifier: Topic :: Scientific/Engineering :: Information Analysis
Classifier: Topic :: Scientific/Engineering :: Mathematics
Classifier: Topic :: Scientific/Engineering :: Visualization
